{
  "training_results": {
    "best_epoch": 51,
    "best_val_metric": "tensor(0.0612)",
    "train_losses": [
      0.6910894338426918,
      0.6078666222506556,
      0.47110406129524623,
      0.4485836799802451,
      0.42891572158912133,
      0.3996772313940114,
      0.38260251694712144,
      0.3691845680105275,
      0.3560609509204996,
      0.3468122374394844,
      0.3422429582168316,
      0.34012626368423987,
      0.3347694914916466,
      0.3316320936227667,
      0.32635710568263615,
      0.32156503457447577,
      0.3212885769276783,
      0.3162781621875434,
      0.31088955032414406,
      0.30850223785844344,
      0.3061590960313534,
      0.3050544282485699,
      0.3006417679375616,
      0.300358512792094,
      0.30010850727558136,
      0.2948203934677716,
      0.2950519287380679,
      0.291747723673952,
      0.2898898088726504,
      0.28978437442204047,
      0.28833996170553666,
      0.28500336100315227,
      0.2854759744529066,
      0.2873398070705348,
      0.2863526986590747,
      0.2844566363712837,
      0.28266590139989195,
      0.2824549135462991,
      0.28251526427680046,
      0.28374371600562126,
      0.2819091297429183,
      0.2832019514050977,
      0.2816257908426482,
      0.2784880995750427,
      0.27882560059942046,
      0.27971026712450486,
      0.2759331189866724,
      0.27615683808408936,
      0.27620919819535883,
      0.2769982861033801,
      0.27492049644733296,
      0.274662413473787,
      0.27630946553986646,
      0.27466387892591543,
      0.27228728990102635,
      0.2724299320373042,
      0.27220648167462186,
      0.2707907631993294,
      0.26824737674203414,
      0.2703675637985098,
      0.2721722005256291,
      0.26616143846306306,
      0.2657200552780053,
      0.261100887224592,
      0.2609079112780505,
      0.2584335218215811,
      0.25841838224180813,
      0.25685989779644997,
      0.2556120393605068,
      0.25419823928125973,
      0.2501409909334676
    ],
    "val_metrics": [
      {
        "precision@5": "tensor(0.0010)",
        "recall@5": "tensor(0.0046)",
        "hit_rate@5": "tensor(0.0051)",
        "ndcg@5": "tensor(0.0030)",
        "map@5": "tensor(0.0023)",
        "mrr@5": "tensor(0.0027)",
        "precision@10": "tensor(0.0013)",
        "recall@10": "tensor(0.0122)",
        "hit_rate@10": "tensor(0.0129)",
        "ndcg@10": "tensor(0.0053)",
        "map@10": "tensor(0.0032)",
        "mrr@10": "tensor(0.0036)",
        "precision@20": "tensor(0.0010)",
        "recall@20": "tensor(0.0190)",
        "hit_rate@20": "tensor(0.0203)",
        "ndcg@20": "tensor(0.0071)",
        "map@20": "tensor(0.0037)",
        "mrr@20": "tensor(0.0041)"
      },
      {
        "precision@5": "tensor(0.0026)",
        "recall@5": "tensor(0.0126)",
        "hit_rate@5": "tensor(0.0130)",
        "ndcg@5": "tensor(0.0090)",
        "map@5": "tensor(0.0077)",
        "mrr@5": "tensor(0.0080)",
        "precision@10": "tensor(0.0021)",
        "recall@10": "tensor(0.0206)",
        "hit_rate@10": "tensor(0.0214)",
        "ndcg@10": "tensor(0.0116)",
        "map@10": "tensor(0.0088)",
        "mrr@10": "tensor(0.0091)",
        "precision@20": "tensor(0.0019)",
        "recall@20": "tensor(0.0371)",
        "hit_rate@20": "tensor(0.0388)",
        "ndcg@20": "tensor(0.0157)",
        "map@20": "tensor(0.0099)",
        "mrr@20": "tensor(0.0102)"
      },
      {
        "precision@5": "tensor(0.0030)",
        "recall@5": "tensor(0.0145)",
        "hit_rate@5": "tensor(0.0151)",
        "ndcg@5": "tensor(0.0090)",
        "map@5": "tensor(0.0071)",
        "mrr@5": "tensor(0.0073)",
        "precision@10": "tensor(0.0030)",
        "recall@10": "tensor(0.0289)",
        "hit_rate@10": "tensor(0.0301)",
        "ndcg@10": "tensor(0.0137)",
        "map@10": "tensor(0.0090)",
        "mrr@10": "tensor(0.0093)",
        "precision@20": "tensor(0.0024)",
        "recall@20": "tensor(0.0460)",
        "hit_rate@20": "tensor(0.0484)",
        "ndcg@20": "tensor(0.0180)",
        "map@20": "tensor(0.0101)",
        "mrr@20": "tensor(0.0106)"
      },
      {
        "precision@5": "tensor(0.0036)",
        "recall@5": "tensor(0.0172)",
        "hit_rate@5": "tensor(0.0179)",
        "ndcg@5": "tensor(0.0115)",
        "map@5": "tensor(0.0095)",
        "mrr@5": "tensor(0.0099)",
        "precision@10": "tensor(0.0029)",
        "recall@10": "tensor(0.0280)",
        "hit_rate@10": "tensor(0.0294)",
        "ndcg@10": "tensor(0.0150)",
        "map@10": "tensor(0.0109)",
        "mrr@10": "tensor(0.0113)",
        "precision@20": "tensor(0.0025)",
        "recall@20": "tensor(0.0468)",
        "hit_rate@20": "tensor(0.0491)",
        "ndcg@20": "tensor(0.0197)",
        "map@20": "tensor(0.0122)",
        "mrr@20": "tensor(0.0127)"
      },
      {
        "precision@5": "tensor(0.0034)",
        "recall@5": "tensor(0.0164)",
        "hit_rate@5": "tensor(0.0171)",
        "ndcg@5": "tensor(0.0105)",
        "map@5": "tensor(0.0085)",
        "mrr@5": "tensor(0.0088)",
        "precision@10": "tensor(0.0027)",
        "recall@10": "tensor(0.0257)",
        "hit_rate@10": "tensor(0.0271)",
        "ndcg@10": "tensor(0.0136)",
        "map@10": "tensor(0.0097)",
        "mrr@10": "tensor(0.0101)",
        "precision@20": "tensor(0.0022)",
        "recall@20": "tensor(0.0413)",
        "hit_rate@20": "tensor(0.0439)",
        "ndcg@20": "tensor(0.0175)",
        "map@20": "tensor(0.0108)",
        "mrr@20": "tensor(0.0113)"
      },
      {
        "precision@5": "tensor(0.0034)",
        "recall@5": "tensor(0.0168)",
        "hit_rate@5": "tensor(0.0172)",
        "ndcg@5": "tensor(0.0109)",
        "map@5": "tensor(0.0089)",
        "mrr@5": "tensor(0.0091)",
        "precision@10": "tensor(0.0028)",
        "recall@10": "tensor(0.0269)",
        "hit_rate@10": "tensor(0.0283)",
        "ndcg@10": "tensor(0.0142)",
        "map@10": "tensor(0.0102)",
        "mrr@10": "tensor(0.0106)",
        "precision@20": "tensor(0.0023)",
        "recall@20": "tensor(0.0432)",
        "hit_rate@20": "tensor(0.0454)",
        "ndcg@20": "tensor(0.0183)",
        "map@20": "tensor(0.0113)",
        "mrr@20": "tensor(0.0117)"
      },
      {
        "precision@5": "tensor(0.0037)",
        "recall@5": "tensor(0.0177)",
        "hit_rate@5": "tensor(0.0184)",
        "ndcg@5": "tensor(0.0116)",
        "map@5": "tensor(0.0095)",
        "mrr@5": "tensor(0.0098)",
        "precision@10": "tensor(0.0030)",
        "recall@10": "tensor(0.0285)",
        "hit_rate@10": "tensor(0.0299)",
        "ndcg@10": "tensor(0.0151)",
        "map@10": "tensor(0.0109)",
        "mrr@10": "tensor(0.0112)",
        "precision@20": "tensor(0.0025)",
        "recall@20": "tensor(0.0475)",
        "hit_rate@20": "tensor(0.0500)",
        "ndcg@20": "tensor(0.0199)",
        "map@20": "tensor(0.0121)",
        "mrr@20": "tensor(0.0126)"
      },
      {
        "precision@5": "tensor(0.0041)",
        "recall@5": "tensor(0.0193)",
        "hit_rate@5": "tensor(0.0203)",
        "ndcg@5": "tensor(0.0126)",
        "map@5": "tensor(0.0103)",
        "mrr@5": "tensor(0.0107)",
        "precision@10": "tensor(0.0032)",
        "recall@10": "tensor(0.0303)",
        "hit_rate@10": "tensor(0.0318)",
        "ndcg@10": "tensor(0.0162)",
        "map@10": "tensor(0.0117)",
        "mrr@10": "tensor(0.0122)",
        "precision@20": "tensor(0.0027)",
        "recall@20": "tensor(0.0506)",
        "hit_rate@20": "tensor(0.0532)",
        "ndcg@20": "tensor(0.0213)",
        "map@20": "tensor(0.0131)",
        "mrr@20": "tensor(0.0137)"
      },
      {
        "precision@5": "tensor(0.0041)",
        "recall@5": "tensor(0.0194)",
        "hit_rate@5": "tensor(0.0203)",
        "ndcg@5": "tensor(0.0131)",
        "map@5": "tensor(0.0108)",
        "mrr@5": "tensor(0.0113)",
        "precision@10": "tensor(0.0033)",
        "recall@10": "tensor(0.0315)",
        "hit_rate@10": "tensor(0.0334)",
        "ndcg@10": "tensor(0.0170)",
        "map@10": "tensor(0.0124)",
        "mrr@10": "tensor(0.0130)",
        "precision@20": "tensor(0.0027)",
        "recall@20": "tensor(0.0507)",
        "hit_rate@20": "tensor(0.0534)",
        "ndcg@20": "tensor(0.0219)",
        "map@20": "tensor(0.0137)",
        "mrr@20": "tensor(0.0144)"
      },
      {
        "precision@5": "tensor(0.0041)",
        "recall@5": "tensor(0.0195)",
        "hit_rate@5": "tensor(0.0205)",
        "ndcg@5": "tensor(0.0135)",
        "map@5": "tensor(0.0113)",
        "mrr@5": "tensor(0.0119)",
        "precision@10": "tensor(0.0032)",
        "recall@10": "tensor(0.0297)",
        "hit_rate@10": "tensor(0.0316)",
        "ndcg@10": "tensor(0.0168)",
        "map@10": "tensor(0.0126)",
        "mrr@10": "tensor(0.0133)",
        "precision@20": "tensor(0.0027)",
        "recall@20": "tensor(0.0502)",
        "hit_rate@20": "tensor(0.0530)",
        "ndcg@20": "tensor(0.0220)",
        "map@20": "tensor(0.0140)",
        "mrr@20": "tensor(0.0148)"
      },
      {
        "precision@5": "tensor(0.0042)",
        "recall@5": "tensor(0.0200)",
        "hit_rate@5": "tensor(0.0211)",
        "ndcg@5": "tensor(0.0134)",
        "map@5": "tensor(0.0110)",
        "mrr@5": "tensor(0.0115)",
        "precision@10": "tensor(0.0035)",
        "recall@10": "tensor(0.0324)",
        "hit_rate@10": "tensor(0.0346)",
        "ndcg@10": "tensor(0.0174)",
        "map@10": "tensor(0.0126)",
        "mrr@10": "tensor(0.0133)",
        "precision@20": "tensor(0.0028)",
        "recall@20": "tensor(0.0521)",
        "hit_rate@20": "tensor(0.0549)",
        "ndcg@20": "tensor(0.0223)",
        "map@20": "tensor(0.0139)",
        "mrr@20": "tensor(0.0146)"
      },
      {
        "precision@5": "tensor(0.0041)",
        "recall@5": "tensor(0.0196)",
        "hit_rate@5": "tensor(0.0207)",
        "ndcg@5": "tensor(0.0131)",
        "map@5": "tensor(0.0108)",
        "mrr@5": "tensor(0.0114)",
        "precision@10": "tensor(0.0034)",
        "recall@10": "tensor(0.0322)",
        "hit_rate@10": "tensor(0.0340)",
        "ndcg@10": "tensor(0.0172)",
        "map@10": "tensor(0.0124)",
        "mrr@10": "tensor(0.0131)",
        "precision@20": "tensor(0.0028)",
        "recall@20": "tensor(0.0536)",
        "hit_rate@20": "tensor(0.0564)",
        "ndcg@20": "tensor(0.0226)",
        "map@20": "tensor(0.0139)",
        "mrr@20": "tensor(0.0146)"
      },
      {
        "precision@5": "tensor(0.0044)",
        "recall@5": "tensor(0.0205)",
        "hit_rate@5": "tensor(0.0218)",
        "ndcg@5": "tensor(0.0134)",
        "map@5": "tensor(0.0108)",
        "mrr@5": "tensor(0.0115)",
        "precision@10": "tensor(0.0036)",
        "recall@10": "tensor(0.0340)",
        "hit_rate@10": "tensor(0.0359)",
        "ndcg@10": "tensor(0.0177)",
        "map@10": "tensor(0.0126)",
        "mrr@10": "tensor(0.0133)",
        "precision@20": "tensor(0.0029)",
        "recall@20": "tensor(0.0545)",
        "hit_rate@20": "tensor(0.0574)",
        "ndcg@20": "tensor(0.0229)",
        "map@20": "tensor(0.0140)",
        "mrr@20": "tensor(0.0147)"
      },
      {
        "precision@5": "tensor(0.0043)",
        "recall@5": "tensor(0.0204)",
        "hit_rate@5": "tensor(0.0217)",
        "ndcg@5": "tensor(0.0137)",
        "map@5": "tensor(0.0113)",
        "mrr@5": "tensor(0.0120)",
        "precision@10": "tensor(0.0036)",
        "recall@10": "tensor(0.0338)",
        "hit_rate@10": "tensor(0.0357)",
        "ndcg@10": "tensor(0.0180)",
        "map@10": "tensor(0.0130)",
        "mrr@10": "tensor(0.0138)",
        "precision@20": "tensor(0.0029)",
        "recall@20": "tensor(0.0545)",
        "hit_rate@20": "tensor(0.0574)",
        "ndcg@20": "tensor(0.0233)",
        "map@20": "tensor(0.0145)",
        "mrr@20": "tensor(0.0152)"
      },
      {
        "precision@5": "tensor(0.0045)",
        "recall@5": "tensor(0.0210)",
        "hit_rate@5": "tensor(0.0223)",
        "ndcg@5": "tensor(0.0137)",
        "map@5": "tensor(0.0112)",
        "mrr@5": "tensor(0.0118)",
        "precision@10": "tensor(0.0035)",
        "recall@10": "tensor(0.0328)",
        "hit_rate@10": "tensor(0.0349)",
        "ndcg@10": "tensor(0.0176)",
        "map@10": "tensor(0.0127)",
        "mrr@10": "tensor(0.0134)",
        "precision@20": "tensor(0.0028)",
        "recall@20": "tensor(0.0527)",
        "hit_rate@20": "tensor(0.0556)",
        "ndcg@20": "tensor(0.0226)",
        "map@20": "tensor(0.0140)",
        "mrr@20": "tensor(0.0148)"
      },
      {
        "precision@5": "tensor(0.0044)",
        "recall@5": "tensor(0.0209)",
        "hit_rate@5": "tensor(0.0221)",
        "ndcg@5": "tensor(0.0142)",
        "map@5": "tensor(0.0118)",
        "mrr@5": "tensor(0.0124)",
        "precision@10": "tensor(0.0036)",
        "recall@10": "tensor(0.0338)",
        "hit_rate@10": "tensor(0.0357)",
        "ndcg@10": "tensor(0.0184)",
        "map@10": "tensor(0.0135)",
        "mrr@10": "tensor(0.0142)",
        "precision@20": "tensor(0.0029)",
        "recall@20": "tensor(0.0545)",
        "hit_rate@20": "tensor(0.0574)",
        "ndcg@20": "tensor(0.0236)",
        "map@20": "tensor(0.0149)",
        "mrr@20": "tensor(0.0156)"
      },
      {
        "precision@5": "tensor(0.0042)",
        "recall@5": "tensor(0.0197)",
        "hit_rate@5": "tensor(0.0210)",
        "ndcg@5": "tensor(0.0131)",
        "map@5": "tensor(0.0108)",
        "mrr@5": "tensor(0.0114)",
        "precision@10": "tensor(0.0034)",
        "recall@10": "tensor(0.0325)",
        "hit_rate@10": "tensor(0.0344)",
        "ndcg@10": "tensor(0.0173)",
        "map@10": "tensor(0.0124)",
        "mrr@10": "tensor(0.0131)",
        "precision@20": "tensor(0.0028)",
        "recall@20": "tensor(0.0534)",
        "hit_rate@20": "tensor(0.0564)",
        "ndcg@20": "tensor(0.0226)",
        "map@20": "tensor(0.0138)",
        "mrr@20": "tensor(0.0146)"
      },
      {
        "precision@5": "tensor(0.0046)",
        "recall@5": "tensor(0.0216)",
        "hit_rate@5": "tensor(0.0230)",
        "ndcg@5": "tensor(0.0143)",
        "map@5": "tensor(0.0116)",
        "mrr@5": "tensor(0.0124)",
        "precision@10": "tensor(0.0037)",
        "recall@10": "tensor(0.0349)",
        "hit_rate@10": "tensor(0.0369)",
        "ndcg@10": "tensor(0.0186)",
        "map@10": "tensor(0.0134)",
        "mrr@10": "tensor(0.0142)",
        "precision@20": "tensor(0.0029)",
        "recall@20": "tensor(0.0551)",
        "hit_rate@20": "tensor(0.0581)",
        "ndcg@20": "tensor(0.0237)",
        "map@20": "tensor(0.0147)",
        "mrr@20": "tensor(0.0156)"
      },
      {
        "precision@5": "tensor(0.0045)",
        "recall@5": "tensor(0.0211)",
        "hit_rate@5": "tensor(0.0225)",
        "ndcg@5": "tensor(0.0142)",
        "map@5": "tensor(0.0117)",
        "mrr@5": "tensor(0.0125)",
        "precision@10": "tensor(0.0036)",
        "recall@10": "tensor(0.0341)",
        "hit_rate@10": "tensor(0.0362)",
        "ndcg@10": "tensor(0.0185)",
        "map@10": "tensor(0.0134)",
        "mrr@10": "tensor(0.0143)",
        "precision@20": "tensor(0.0029)",
        "recall@20": "tensor(0.0554)",
        "hit_rate@20": "tensor(0.0585)",
        "ndcg@20": "tensor(0.0239)",
        "map@20": "tensor(0.0149)",
        "mrr@20": "tensor(0.0158)"
      },
      {
        "precision@5": "tensor(0.0043)",
        "recall@5": "tensor(0.0204)",
        "hit_rate@5": "tensor(0.0217)",
        "ndcg@5": "tensor(0.0141)",
        "map@5": "tensor(0.0117)",
        "mrr@5": "tensor(0.0124)",
        "precision@10": "tensor(0.0037)",
        "recall@10": "tensor(0.0350)",
        "hit_rate@10": "tensor(0.0367)",
        "ndcg@10": "tensor(0.0187)",
        "map@10": "tensor(0.0136)",
        "mrr@10": "tensor(0.0144)",
        "precision@20": "tensor(0.0030)",
        "recall@20": "tensor(0.0570)",
        "hit_rate@20": "tensor(0.0599)",
        "ndcg@20": "tensor(0.0243)",
        "map@20": "tensor(0.0151)",
        "mrr@20": "tensor(0.0160)"
      },
      {
        "precision@5": "tensor(0.0046)",
        "recall@5": "tensor(0.0218)",
        "hit_rate@5": "tensor(0.0230)",
        "ndcg@5": "tensor(0.0146)",
        "map@5": "tensor(0.0120)",
        "mrr@5": "tensor(0.0126)",
        "precision@10": "tensor(0.0037)",
        "recall@10": "tensor(0.0355)",
        "hit_rate@10": "tensor(0.0373)",
        "ndcg@10": "tensor(0.0190)",
        "map@10": "tensor(0.0137)",
        "mrr@10": "tensor(0.0145)",
        "precision@20": "tensor(0.0031)",
        "recall@20": "tensor(0.0584)",
        "hit_rate@20": "tensor(0.0615)",
        "ndcg@20": "tensor(0.0248)",
        "map@20": "tensor(0.0153)",
        "mrr@20": "tensor(0.0161)"
      },
      {
        "precision@5": "tensor(0.0044)",
        "recall@5": "tensor(0.0206)",
        "hit_rate@5": "tensor(0.0220)",
        "ndcg@5": "tensor(0.0139)",
        "map@5": "tensor(0.0115)",
        "mrr@5": "tensor(0.0123)",
        "precision@10": "tensor(0.0037)",
        "recall@10": "tensor(0.0345)",
        "hit_rate@10": "tensor(0.0368)",
        "ndcg@10": "tensor(0.0185)",
        "map@10": "tensor(0.0133)",
        "mrr@10": "tensor(0.0142)",
        "precision@20": "tensor(0.0030)",
        "recall@20": "tensor(0.0570)",
        "hit_rate@20": "tensor(0.0602)",
        "ndcg@20": "tensor(0.0242)",
        "map@20": "tensor(0.0148)",
        "mrr@20": "tensor(0.0158)"
      },
      {
        "precision@5": "tensor(0.0045)",
        "recall@5": "tensor(0.0212)",
        "hit_rate@5": "tensor(0.0225)",
        "ndcg@5": "tensor(0.0141)",
        "map@5": "tensor(0.0115)",
        "mrr@5": "tensor(0.0122)",
        "precision@10": "tensor(0.0037)",
        "recall@10": "tensor(0.0347)",
        "hit_rate@10": "tensor(0.0366)",
        "ndcg@10": "tensor(0.0184)",
        "map@10": "tensor(0.0133)",
        "mrr@10": "tensor(0.0141)",
        "precision@20": "tensor(0.0030)",
        "recall@20": "tensor(0.0570)",
        "hit_rate@20": "tensor(0.0600)",
        "ndcg@20": "tensor(0.0241)",
        "map@20": "tensor(0.0148)",
        "mrr@20": "tensor(0.0157)"
      },
      {
        "precision@5": "tensor(0.0047)",
        "recall@5": "tensor(0.0222)",
        "hit_rate@5": "tensor(0.0235)",
        "ndcg@5": "tensor(0.0146)",
        "map@5": "tensor(0.0119)",
        "mrr@5": "tensor(0.0126)",
        "precision@10": "tensor(0.0038)",
        "recall@10": "tensor(0.0355)",
        "hit_rate@10": "tensor(0.0376)",
        "ndcg@10": "tensor(0.0189)",
        "map@10": "tensor(0.0136)",
        "mrr@10": "tensor(0.0144)",
        "precision@20": "tensor(0.0031)",
        "recall@20": "tensor(0.0582)",
        "hit_rate@20": "tensor(0.0614)",
        "ndcg@20": "tensor(0.0247)",
        "map@20": "tensor(0.0152)",
        "mrr@20": "tensor(0.0160)"
      },
      {
        "precision@5": "tensor(0.0044)",
        "recall@5": "tensor(0.0207)",
        "hit_rate@5": "tensor(0.0221)",
        "ndcg@5": "tensor(0.0139)",
        "map@5": "tensor(0.0115)",
        "mrr@5": "tensor(0.0123)",
        "precision@10": "tensor(0.0037)",
        "recall@10": "tensor(0.0348)",
        "hit_rate@10": "tensor(0.0368)",
        "ndcg@10": "tensor(0.0185)",
        "map@10": "tensor(0.0134)",
        "mrr@10": "tensor(0.0142)",
        "precision@20": "tensor(0.0031)",
        "recall@20": "tensor(0.0578)",
        "hit_rate@20": "tensor(0.0607)",
        "ndcg@20": "tensor(0.0244)",
        "map@20": "tensor(0.0149)",
        "mrr@20": "tensor(0.0158)"
      },
      {
        "precision@5": "tensor(0.0045)",
        "recall@5": "tensor(0.0212)",
        "hit_rate@5": "tensor(0.0225)",
        "ndcg@5": "tensor(0.0141)",
        "map@5": "tensor(0.0116)",
        "mrr@5": "tensor(0.0123)",
        "precision@10": "tensor(0.0039)",
        "recall@10": "tensor(0.0363)",
        "hit_rate@10": "tensor(0.0385)",
        "ndcg@10": "tensor(0.0190)",
        "map@10": "tensor(0.0135)",
        "mrr@10": "tensor(0.0144)",
        "precision@20": "tensor(0.0031)",
        "recall@20": "tensor(0.0585)",
        "hit_rate@20": "tensor(0.0616)",
        "ndcg@20": "tensor(0.0247)",
        "map@20": "tensor(0.0151)",
        "mrr@20": "tensor(0.0159)"
      },
      {
        "precision@5": "tensor(0.0046)",
        "recall@5": "tensor(0.0218)",
        "hit_rate@5": "tensor(0.0232)",
        "ndcg@5": "tensor(0.0144)",
        "map@5": "tensor(0.0116)",
        "mrr@5": "tensor(0.0124)",
        "precision@10": "tensor(0.0038)",
        "recall@10": "tensor(0.0354)",
        "hit_rate@10": "tensor(0.0376)",
        "ndcg@10": "tensor(0.0188)",
        "map@10": "tensor(0.0134)",
        "mrr@10": "tensor(0.0143)",
        "precision@20": "tensor(0.0031)",
        "recall@20": "tensor(0.0576)",
        "hit_rate@20": "tensor(0.0608)",
        "ndcg@20": "tensor(0.0244)",
        "map@20": "tensor(0.0149)",
        "mrr@20": "tensor(0.0159)"
      },
      {
        "precision@5": "tensor(0.0047)",
        "recall@5": "tensor(0.0221)",
        "hit_rate@5": "tensor(0.0233)",
        "ndcg@5": "tensor(0.0144)",
        "map@5": "tensor(0.0117)",
        "mrr@5": "tensor(0.0124)",
        "precision@10": "tensor(0.0038)",
        "recall@10": "tensor(0.0357)",
        "hit_rate@10": "tensor(0.0380)",
        "ndcg@10": "tensor(0.0188)",
        "map@10": "tensor(0.0134)",
        "mrr@10": "tensor(0.0143)",
        "precision@20": "tensor(0.0031)",
        "recall@20": "tensor(0.0582)",
        "hit_rate@20": "tensor(0.0614)",
        "ndcg@20": "tensor(0.0245)",
        "map@20": "tensor(0.0150)",
        "mrr@20": "tensor(0.0159)"
      },
      {
        "precision@5": "tensor(0.0046)",
        "recall@5": "tensor(0.0214)",
        "hit_rate@5": "tensor(0.0227)",
        "ndcg@5": "tensor(0.0141)",
        "map@5": "tensor(0.0115)",
        "mrr@5": "tensor(0.0122)",
        "precision@10": "tensor(0.0038)",
        "recall@10": "tensor(0.0356)",
        "hit_rate@10": "tensor(0.0376)",
        "ndcg@10": "tensor(0.0187)",
        "map@10": "tensor(0.0133)",
        "mrr@10": "tensor(0.0141)",
        "precision@20": "tensor(0.0031)",
        "recall@20": "tensor(0.0594)",
        "hit_rate@20": "tensor(0.0625)",
        "ndcg@20": "tensor(0.0247)",
        "map@20": "tensor(0.0150)",
        "mrr@20": "tensor(0.0158)"
      },
      {
        "precision@5": "tensor(0.0047)",
        "recall@5": "tensor(0.0224)",
        "hit_rate@5": "tensor(0.0237)",
        "ndcg@5": "tensor(0.0150)",
        "map@5": "tensor(0.0124)",
        "mrr@5": "tensor(0.0131)",
        "precision@10": "tensor(0.0037)",
        "recall@10": "tensor(0.0350)",
        "hit_rate@10": "tensor(0.0371)",
        "ndcg@10": "tensor(0.0191)",
        "map@10": "tensor(0.0141)",
        "mrr@10": "tensor(0.0148)",
        "precision@20": "tensor(0.0031)",
        "recall@20": "tensor(0.0589)",
        "hit_rate@20": "tensor(0.0619)",
        "ndcg@20": "tensor(0.0252)",
        "map@20": "tensor(0.0157)",
        "mrr@20": "tensor(0.0165)"
      },
      {
        "precision@5": "tensor(0.0048)",
        "recall@5": "tensor(0.0228)",
        "hit_rate@5": "tensor(0.0242)",
        "ndcg@5": "tensor(0.0147)",
        "map@5": "tensor(0.0118)",
        "mrr@5": "tensor(0.0124)",
        "precision@10": "tensor(0.0038)",
        "recall@10": "tensor(0.0359)",
        "hit_rate@10": "tensor(0.0382)",
        "ndcg@10": "tensor(0.0189)",
        "map@10": "tensor(0.0135)",
        "mrr@10": "tensor(0.0143)",
        "precision@20": "tensor(0.0032)",
        "recall@20": "tensor(0.0601)",
        "hit_rate@20": "tensor(0.0634)",
        "ndcg@20": "tensor(0.0251)",
        "map@20": "tensor(0.0151)",
        "mrr@20": "tensor(0.0160)"
      },
      {
        "precision@5": "tensor(0.0047)",
        "recall@5": "tensor(0.0222)",
        "hit_rate@5": "tensor(0.0236)",
        "ndcg@5": "tensor(0.0147)",
        "map@5": "tensor(0.0121)",
        "mrr@5": "tensor(0.0127)",
        "precision@10": "tensor(0.0039)",
        "recall@10": "tensor(0.0364)",
        "hit_rate@10": "tensor(0.0386)",
        "ndcg@10": "tensor(0.0193)",
        "map@10": "tensor(0.0139)",
        "mrr@10": "tensor(0.0147)",
        "precision@20": "tensor(0.0032)",
        "recall@20": "tensor(0.0599)",
        "hit_rate@20": "tensor(0.0633)",
        "ndcg@20": "tensor(0.0253)",
        "map@20": "tensor(0.0155)",
        "mrr@20": "tensor(0.0163)"
      },
      {
        "precision@5": "tensor(0.0046)",
        "recall@5": "tensor(0.0215)",
        "hit_rate@5": "tensor(0.0228)",
        "ndcg@5": "tensor(0.0143)",
        "map@5": "tensor(0.0117)",
        "mrr@5": "tensor(0.0123)",
        "precision@10": "tensor(0.0038)",
        "recall@10": "tensor(0.0357)",
        "hit_rate@10": "tensor(0.0378)",
        "ndcg@10": "tensor(0.0189)",
        "map@10": "tensor(0.0135)",
        "mrr@10": "tensor(0.0143)",
        "precision@20": "tensor(0.0031)",
        "recall@20": "tensor(0.0594)",
        "hit_rate@20": "tensor(0.0623)",
        "ndcg@20": "tensor(0.0249)",
        "map@20": "tensor(0.0152)",
        "mrr@20": "tensor(0.0160)"
      },
      {
        "precision@5": "tensor(0.0045)",
        "recall@5": "tensor(0.0210)",
        "hit_rate@5": "tensor(0.0223)",
        "ndcg@5": "tensor(0.0139)",
        "map@5": "tensor(0.0114)",
        "mrr@5": "tensor(0.0121)",
        "precision@10": "tensor(0.0037)",
        "recall@10": "tensor(0.0352)",
        "hit_rate@10": "tensor(0.0373)",
        "ndcg@10": "tensor(0.0185)",
        "map@10": "tensor(0.0132)",
        "mrr@10": "tensor(0.0140)",
        "precision@20": "tensor(0.0031)",
        "recall@20": "tensor(0.0594)",
        "hit_rate@20": "tensor(0.0624)",
        "ndcg@20": "tensor(0.0247)",
        "map@20": "tensor(0.0149)",
        "mrr@20": "tensor(0.0157)"
      },
      {
        "precision@5": "tensor(0.0045)",
        "recall@5": "tensor(0.0213)",
        "hit_rate@5": "tensor(0.0227)",
        "ndcg@5": "tensor(0.0144)",
        "map@5": "tensor(0.0119)",
        "mrr@5": "tensor(0.0127)",
        "precision@10": "tensor(0.0039)",
        "recall@10": "tensor(0.0369)",
        "hit_rate@10": "tensor(0.0392)",
        "ndcg@10": "tensor(0.0195)",
        "map@10": "tensor(0.0140)",
        "mrr@10": "tensor(0.0148)",
        "precision@20": "tensor(0.0032)",
        "recall@20": "tensor(0.0602)",
        "hit_rate@20": "tensor(0.0635)",
        "ndcg@20": "tensor(0.0254)",
        "map@20": "tensor(0.0155)",
        "mrr@20": "tensor(0.0165)"
      },
      {
        "precision@5": "tensor(0.0046)",
        "recall@5": "tensor(0.0217)",
        "hit_rate@5": "tensor(0.0230)",
        "ndcg@5": "tensor(0.0144)",
        "map@5": "tensor(0.0118)",
        "mrr@5": "tensor(0.0126)",
        "precision@10": "tensor(0.0038)",
        "recall@10": "tensor(0.0362)",
        "hit_rate@10": "tensor(0.0381)",
        "ndcg@10": "tensor(0.0191)",
        "map@10": "tensor(0.0137)",
        "mrr@10": "tensor(0.0145)",
        "precision@20": "tensor(0.0032)",
        "recall@20": "tensor(0.0598)",
        "hit_rate@20": "tensor(0.0628)",
        "ndcg@20": "tensor(0.0252)",
        "map@20": "tensor(0.0154)",
        "mrr@20": "tensor(0.0162)"
      },
      {
        "precision@5": "tensor(0.0046)",
        "recall@5": "tensor(0.0215)",
        "hit_rate@5": "tensor(0.0229)",
        "ndcg@5": "tensor(0.0143)",
        "map@5": "tensor(0.0116)",
        "mrr@5": "tensor(0.0124)",
        "precision@10": "tensor(0.0039)",
        "recall@10": "tensor(0.0364)",
        "hit_rate@10": "tensor(0.0386)",
        "ndcg@10": "tensor(0.0191)",
        "map@10": "tensor(0.0136)",
        "mrr@10": "tensor(0.0144)",
        "precision@20": "tensor(0.0032)",
        "recall@20": "tensor(0.0600)",
        "hit_rate@20": "tensor(0.0633)",
        "ndcg@20": "tensor(0.0251)",
        "map@20": "tensor(0.0152)",
        "mrr@20": "tensor(0.0161)"
      },
      {
        "precision@5": "tensor(0.0047)",
        "recall@5": "tensor(0.0221)",
        "hit_rate@5": "tensor(0.0235)",
        "ndcg@5": "tensor(0.0145)",
        "map@5": "tensor(0.0117)",
        "mrr@5": "tensor(0.0124)",
        "precision@10": "tensor(0.0039)",
        "recall@10": "tensor(0.0369)",
        "hit_rate@10": "tensor(0.0390)",
        "ndcg@10": "tensor(0.0193)",
        "map@10": "tensor(0.0137)",
        "mrr@10": "tensor(0.0144)",
        "precision@20": "tensor(0.0032)",
        "recall@20": "tensor(0.0607)",
        "hit_rate@20": "tensor(0.0639)",
        "ndcg@20": "tensor(0.0253)",
        "map@20": "tensor(0.0153)",
        "mrr@20": "tensor(0.0161)"
      },
      {
        "precision@5": "tensor(0.0046)",
        "recall@5": "tensor(0.0218)",
        "hit_rate@5": "tensor(0.0232)",
        "ndcg@5": "tensor(0.0139)",
        "map@5": "tensor(0.0111)",
        "mrr@5": "tensor(0.0119)",
        "precision@10": "tensor(0.0039)",
        "recall@10": "tensor(0.0364)",
        "hit_rate@10": "tensor(0.0385)",
        "ndcg@10": "tensor(0.0187)",
        "map@10": "tensor(0.0130)",
        "mrr@10": "tensor(0.0139)",
        "precision@20": "tensor(0.0031)",
        "recall@20": "tensor(0.0588)",
        "hit_rate@20": "tensor(0.0622)",
        "ndcg@20": "tensor(0.0244)",
        "map@20": "tensor(0.0146)",
        "mrr@20": "tensor(0.0155)"
      },
      {
        "precision@5": "tensor(0.0046)",
        "recall@5": "tensor(0.0216)",
        "hit_rate@5": "tensor(0.0230)",
        "ndcg@5": "tensor(0.0142)",
        "map@5": "tensor(0.0115)",
        "mrr@5": "tensor(0.0123)",
        "precision@10": "tensor(0.0039)",
        "recall@10": "tensor(0.0366)",
        "hit_rate@10": "tensor(0.0388)",
        "ndcg@10": "tensor(0.0190)",
        "map@10": "tensor(0.0135)",
        "mrr@10": "tensor(0.0143)",
        "precision@20": "tensor(0.0031)",
        "recall@20": "tensor(0.0587)",
        "hit_rate@20": "tensor(0.0620)",
        "ndcg@20": "tensor(0.0246)",
        "map@20": "tensor(0.0150)",
        "mrr@20": "tensor(0.0159)"
      },
      {
        "precision@5": "tensor(0.0048)",
        "recall@5": "tensor(0.0225)",
        "hit_rate@5": "tensor(0.0238)",
        "ndcg@5": "tensor(0.0147)",
        "map@5": "tensor(0.0120)",
        "mrr@5": "tensor(0.0126)",
        "precision@10": "tensor(0.0041)",
        "recall@10": "tensor(0.0385)",
        "hit_rate@10": "tensor(0.0405)",
        "ndcg@10": "tensor(0.0199)",
        "map@10": "tensor(0.0140)",
        "mrr@10": "tensor(0.0147)",
        "precision@20": "tensor(0.0032)",
        "recall@20": "tensor(0.0608)",
        "hit_rate@20": "tensor(0.0642)",
        "ndcg@20": "tensor(0.0256)",
        "map@20": "tensor(0.0156)",
        "mrr@20": "tensor(0.0163)"
      },
      {
        "precision@5": "tensor(0.0046)",
        "recall@5": "tensor(0.0218)",
        "hit_rate@5": "tensor(0.0231)",
        "ndcg@5": "tensor(0.0147)",
        "map@5": "tensor(0.0121)",
        "mrr@5": "tensor(0.0128)",
        "precision@10": "tensor(0.0037)",
        "recall@10": "tensor(0.0350)",
        "hit_rate@10": "tensor(0.0370)",
        "ndcg@10": "tensor(0.0189)",
        "map@10": "tensor(0.0138)",
        "mrr@10": "tensor(0.0146)",
        "precision@20": "tensor(0.0031)",
        "recall@20": "tensor(0.0595)",
        "hit_rate@20": "tensor(0.0626)",
        "ndcg@20": "tensor(0.0251)",
        "map@20": "tensor(0.0155)",
        "mrr@20": "tensor(0.0163)"
      },
      {
        "precision@5": "tensor(0.0048)",
        "recall@5": "tensor(0.0227)",
        "hit_rate@5": "tensor(0.0241)",
        "ndcg@5": "tensor(0.0153)",
        "map@5": "tensor(0.0127)",
        "mrr@5": "tensor(0.0134)",
        "precision@10": "tensor(0.0038)",
        "recall@10": "tensor(0.0359)",
        "hit_rate@10": "tensor(0.0379)",
        "ndcg@10": "tensor(0.0196)",
        "map@10": "tensor(0.0144)",
        "mrr@10": "tensor(0.0152)",
        "precision@20": "tensor(0.0032)",
        "recall@20": "tensor(0.0605)",
        "hit_rate@20": "tensor(0.0638)",
        "ndcg@20": "tensor(0.0259)",
        "map@20": "tensor(0.0161)",
        "mrr@20": "tensor(0.0170)"
      },
      {
        "precision@5": "tensor(0.0046)",
        "recall@5": "tensor(0.0215)",
        "hit_rate@5": "tensor(0.0230)",
        "ndcg@5": "tensor(0.0140)",
        "map@5": "tensor(0.0112)",
        "mrr@5": "tensor(0.0120)",
        "precision@10": "tensor(0.0039)",
        "recall@10": "tensor(0.0368)",
        "hit_rate@10": "tensor(0.0391)",
        "ndcg@10": "tensor(0.0189)",
        "map@10": "tensor(0.0132)",
        "mrr@10": "tensor(0.0141)",
        "precision@20": "tensor(0.0032)",
        "recall@20": "tensor(0.0605)",
        "hit_rate@20": "tensor(0.0638)",
        "ndcg@20": "tensor(0.0249)",
        "map@20": "tensor(0.0148)",
        "mrr@20": "tensor(0.0158)"
      },
      {
        "precision@5": "tensor(0.0046)",
        "recall@5": "tensor(0.0217)",
        "hit_rate@5": "tensor(0.0230)",
        "ndcg@5": "tensor(0.0142)",
        "map@5": "tensor(0.0115)",
        "mrr@5": "tensor(0.0122)",
        "precision@10": "tensor(0.0040)",
        "recall@10": "tensor(0.0374)",
        "hit_rate@10": "tensor(0.0396)",
        "ndcg@10": "tensor(0.0193)",
        "map@10": "tensor(0.0136)",
        "mrr@10": "tensor(0.0143)",
        "precision@20": "tensor(0.0032)",
        "recall@20": "tensor(0.0603)",
        "hit_rate@20": "tensor(0.0637)",
        "ndcg@20": "tensor(0.0251)",
        "map@20": "tensor(0.0151)",
        "mrr@20": "tensor(0.0160)"
      },
      {
        "precision@5": "tensor(0.0044)",
        "recall@5": "tensor(0.0205)",
        "hit_rate@5": "tensor(0.0220)",
        "ndcg@5": "tensor(0.0138)",
        "map@5": "tensor(0.0113)",
        "mrr@5": "tensor(0.0121)",
        "precision@10": "tensor(0.0037)",
        "recall@10": "tensor(0.0351)",
        "hit_rate@10": "tensor(0.0373)",
        "ndcg@10": "tensor(0.0185)",
        "map@10": "tensor(0.0132)",
        "mrr@10": "tensor(0.0141)",
        "precision@20": "tensor(0.0032)",
        "recall@20": "tensor(0.0606)",
        "hit_rate@20": "tensor(0.0638)",
        "ndcg@20": "tensor(0.0250)",
        "map@20": "tensor(0.0150)",
        "mrr@20": "tensor(0.0159)"
      },
      {
        "precision@5": "tensor(0.0045)",
        "recall@5": "tensor(0.0209)",
        "hit_rate@5": "tensor(0.0224)",
        "ndcg@5": "tensor(0.0138)",
        "map@5": "tensor(0.0112)",
        "mrr@5": "tensor(0.0120)",
        "precision@10": "tensor(0.0037)",
        "recall@10": "tensor(0.0349)",
        "hit_rate@10": "tensor(0.0369)",
        "ndcg@10": "tensor(0.0183)",
        "map@10": "tensor(0.0130)",
        "mrr@10": "tensor(0.0139)",
        "precision@20": "tensor(0.0032)",
        "recall@20": "tensor(0.0596)",
        "hit_rate@20": "tensor(0.0629)",
        "ndcg@20": "tensor(0.0246)",
        "map@20": "tensor(0.0147)",
        "mrr@20": "tensor(0.0157)"
      },
      {
        "precision@5": "tensor(0.0046)",
        "recall@5": "tensor(0.0218)",
        "hit_rate@5": "tensor(0.0231)",
        "ndcg@5": "tensor(0.0143)",
        "map@5": "tensor(0.0117)",
        "mrr@5": "tensor(0.0123)",
        "precision@10": "tensor(0.0039)",
        "recall@10": "tensor(0.0364)",
        "hit_rate@10": "tensor(0.0386)",
        "ndcg@10": "tensor(0.0191)",
        "map@10": "tensor(0.0136)",
        "mrr@10": "tensor(0.0143)",
        "precision@20": "tensor(0.0032)",
        "recall@20": "tensor(0.0612)",
        "hit_rate@20": "tensor(0.0645)",
        "ndcg@20": "tensor(0.0253)",
        "map@20": "tensor(0.0152)",
        "mrr@20": "tensor(0.0161)"
      },
      {
        "precision@5": "tensor(0.0045)",
        "recall@5": "tensor(0.0210)",
        "hit_rate@5": "tensor(0.0225)",
        "ndcg@5": "tensor(0.0144)",
        "map@5": "tensor(0.0120)",
        "mrr@5": "tensor(0.0127)",
        "precision@10": "tensor(0.0039)",
        "recall@10": "tensor(0.0364)",
        "hit_rate@10": "tensor(0.0385)",
        "ndcg@10": "tensor(0.0193)",
        "map@10": "tensor(0.0139)",
        "mrr@10": "tensor(0.0148)",
        "precision@20": "tensor(0.0032)",
        "recall@20": "tensor(0.0598)",
        "hit_rate@20": "tensor(0.0628)",
        "ndcg@20": "tensor(0.0253)",
        "map@20": "tensor(0.0155)",
        "mrr@20": "tensor(0.0165)"
      },
      {
        "precision@5": "tensor(0.0045)",
        "recall@5": "tensor(0.0211)",
        "hit_rate@5": "tensor(0.0224)",
        "ndcg@5": "tensor(0.0140)",
        "map@5": "tensor(0.0115)",
        "mrr@5": "tensor(0.0122)",
        "precision@10": "tensor(0.0039)",
        "recall@10": "tensor(0.0361)",
        "hit_rate@10": "tensor(0.0384)",
        "ndcg@10": "tensor(0.0189)",
        "map@10": "tensor(0.0135)",
        "mrr@10": "tensor(0.0143)",
        "precision@20": "tensor(0.0032)",
        "recall@20": "tensor(0.0597)",
        "hit_rate@20": "tensor(0.0630)",
        "ndcg@20": "tensor(0.0249)",
        "map@20": "tensor(0.0151)",
        "mrr@20": "tensor(0.0160)"
      },
      {
        "precision@5": "tensor(0.0048)",
        "recall@5": "tensor(0.0225)",
        "hit_rate@5": "tensor(0.0240)",
        "ndcg@5": "tensor(0.0147)",
        "map@5": "tensor(0.0119)",
        "mrr@5": "tensor(0.0126)",
        "precision@10": "tensor(0.0040)",
        "recall@10": "tensor(0.0372)",
        "hit_rate@10": "tensor(0.0394)",
        "ndcg@10": "tensor(0.0194)",
        "map@10": "tensor(0.0138)",
        "mrr@10": "tensor(0.0146)",
        "precision@20": "tensor(0.0032)",
        "recall@20": "tensor(0.0612)",
        "hit_rate@20": "tensor(0.0645)",
        "ndcg@20": "tensor(0.0255)",
        "map@20": "tensor(0.0154)",
        "mrr@20": "tensor(0.0163)"
      },
      {
        "precision@5": "tensor(0.0046)",
        "recall@5": "tensor(0.0216)",
        "hit_rate@5": "tensor(0.0230)",
        "ndcg@5": "tensor(0.0143)",
        "map@5": "tensor(0.0117)",
        "mrr@5": "tensor(0.0125)",
        "precision@10": "tensor(0.0039)",
        "recall@10": "tensor(0.0370)",
        "hit_rate@10": "tensor(0.0392)",
        "ndcg@10": "tensor(0.0193)",
        "map@10": "tensor(0.0137)",
        "mrr@10": "tensor(0.0146)",
        "precision@20": "tensor(0.0031)",
        "recall@20": "tensor(0.0586)",
        "hit_rate@20": "tensor(0.0621)",
        "ndcg@20": "tensor(0.0249)",
        "map@20": "tensor(0.0152)",
        "mrr@20": "tensor(0.0162)"
      },
      {
        "precision@5": "tensor(0.0046)",
        "recall@5": "tensor(0.0213)",
        "hit_rate@5": "tensor(0.0227)",
        "ndcg@5": "tensor(0.0144)",
        "map@5": "tensor(0.0119)",
        "mrr@5": "tensor(0.0126)",
        "precision@10": "tensor(0.0039)",
        "recall@10": "tensor(0.0365)",
        "hit_rate@10": "tensor(0.0387)",
        "ndcg@10": "tensor(0.0193)",
        "map@10": "tensor(0.0139)",
        "mrr@10": "tensor(0.0146)",
        "precision@20": "tensor(0.0032)",
        "recall@20": "tensor(0.0602)",
        "hit_rate@20": "tensor(0.0637)",
        "ndcg@20": "tensor(0.0254)",
        "map@20": "tensor(0.0155)",
        "mrr@20": "tensor(0.0164)"
      },
      {
        "precision@5": "tensor(0.0044)",
        "recall@5": "tensor(0.0207)",
        "hit_rate@5": "tensor(0.0220)",
        "ndcg@5": "tensor(0.0139)",
        "map@5": "tensor(0.0114)",
        "mrr@5": "tensor(0.0121)",
        "precision@10": "tensor(0.0038)",
        "recall@10": "tensor(0.0358)",
        "hit_rate@10": "tensor(0.0380)",
        "ndcg@10": "tensor(0.0187)",
        "map@10": "tensor(0.0133)",
        "mrr@10": "tensor(0.0141)",
        "precision@20": "tensor(0.0032)",
        "recall@20": "tensor(0.0595)",
        "hit_rate@20": "tensor(0.0626)",
        "ndcg@20": "tensor(0.0247)",
        "map@20": "tensor(0.0150)",
        "mrr@20": "tensor(0.0158)"
      },
      {
        "precision@5": "tensor(0.0045)",
        "recall@5": "tensor(0.0211)",
        "hit_rate@5": "tensor(0.0226)",
        "ndcg@5": "tensor(0.0142)",
        "map@5": "tensor(0.0117)",
        "mrr@5": "tensor(0.0124)",
        "precision@10": "tensor(0.0038)",
        "recall@10": "tensor(0.0361)",
        "hit_rate@10": "tensor(0.0382)",
        "ndcg@10": "tensor(0.0191)",
        "map@10": "tensor(0.0137)",
        "mrr@10": "tensor(0.0145)",
        "precision@20": "tensor(0.0032)",
        "recall@20": "tensor(0.0599)",
        "hit_rate@20": "tensor(0.0633)",
        "ndcg@20": "tensor(0.0251)",
        "map@20": "tensor(0.0153)",
        "mrr@20": "tensor(0.0162)"
      },
      {
        "precision@5": "tensor(0.0047)",
        "recall@5": "tensor(0.0221)",
        "hit_rate@5": "tensor(0.0235)",
        "ndcg@5": "tensor(0.0145)",
        "map@5": "tensor(0.0118)",
        "mrr@5": "tensor(0.0125)",
        "precision@10": "tensor(0.0039)",
        "recall@10": "tensor(0.0368)",
        "hit_rate@10": "tensor(0.0390)",
        "ndcg@10": "tensor(0.0193)",
        "map@10": "tensor(0.0137)",
        "mrr@10": "tensor(0.0145)",
        "precision@20": "tensor(0.0032)",
        "recall@20": "tensor(0.0611)",
        "hit_rate@20": "tensor(0.0646)",
        "ndcg@20": "tensor(0.0254)",
        "map@20": "tensor(0.0153)",
        "mrr@20": "tensor(0.0162)"
      },
      {
        "precision@5": "tensor(0.0045)",
        "recall@5": "tensor(0.0212)",
        "hit_rate@5": "tensor(0.0225)",
        "ndcg@5": "tensor(0.0140)",
        "map@5": "tensor(0.0114)",
        "mrr@5": "tensor(0.0120)",
        "precision@10": "tensor(0.0038)",
        "recall@10": "tensor(0.0357)",
        "hit_rate@10": "tensor(0.0378)",
        "ndcg@10": "tensor(0.0187)",
        "map@10": "tensor(0.0133)",
        "mrr@10": "tensor(0.0140)",
        "precision@20": "tensor(0.0031)",
        "recall@20": "tensor(0.0578)",
        "hit_rate@20": "tensor(0.0612)",
        "ndcg@20": "tensor(0.0243)",
        "map@20": "tensor(0.0148)",
        "mrr@20": "tensor(0.0156)"
      },
      {
        "precision@5": "tensor(0.0045)",
        "recall@5": "tensor(0.0212)",
        "hit_rate@5": "tensor(0.0224)",
        "ndcg@5": "tensor(0.0140)",
        "map@5": "tensor(0.0115)",
        "mrr@5": "tensor(0.0121)",
        "precision@10": "tensor(0.0038)",
        "recall@10": "tensor(0.0358)",
        "hit_rate@10": "tensor(0.0380)",
        "ndcg@10": "tensor(0.0188)",
        "map@10": "tensor(0.0134)",
        "mrr@10": "tensor(0.0141)",
        "precision@20": "tensor(0.0032)",
        "recall@20": "tensor(0.0596)",
        "hit_rate@20": "tensor(0.0629)",
        "ndcg@20": "tensor(0.0248)",
        "map@20": "tensor(0.0150)",
        "mrr@20": "tensor(0.0159)"
      },
      {
        "precision@5": "tensor(0.0047)",
        "recall@5": "tensor(0.0221)",
        "hit_rate@5": "tensor(0.0233)",
        "ndcg@5": "tensor(0.0146)",
        "map@5": "tensor(0.0119)",
        "mrr@5": "tensor(0.0125)",
        "precision@10": "tensor(0.0038)",
        "recall@10": "tensor(0.0361)",
        "hit_rate@10": "tensor(0.0382)",
        "ndcg@10": "tensor(0.0191)",
        "map@10": "tensor(0.0137)",
        "mrr@10": "tensor(0.0145)",
        "precision@20": "tensor(0.0032)",
        "recall@20": "tensor(0.0594)",
        "hit_rate@20": "tensor(0.0628)",
        "ndcg@20": "tensor(0.0250)",
        "map@20": "tensor(0.0153)",
        "mrr@20": "tensor(0.0161)"
      },
      {
        "precision@5": "tensor(0.0045)",
        "recall@5": "tensor(0.0213)",
        "hit_rate@5": "tensor(0.0226)",
        "ndcg@5": "tensor(0.0140)",
        "map@5": "tensor(0.0114)",
        "mrr@5": "tensor(0.0120)",
        "precision@10": "tensor(0.0038)",
        "recall@10": "tensor(0.0355)",
        "hit_rate@10": "tensor(0.0376)",
        "ndcg@10": "tensor(0.0186)",
        "map@10": "tensor(0.0132)",
        "mrr@10": "tensor(0.0140)",
        "precision@20": "tensor(0.0032)",
        "recall@20": "tensor(0.0604)",
        "hit_rate@20": "tensor(0.0636)",
        "ndcg@20": "tensor(0.0249)",
        "map@20": "tensor(0.0149)",
        "mrr@20": "tensor(0.0157)"
      },
      {
        "precision@5": "tensor(0.0045)",
        "recall@5": "tensor(0.0213)",
        "hit_rate@5": "tensor(0.0227)",
        "ndcg@5": "tensor(0.0139)",
        "map@5": "tensor(0.0113)",
        "mrr@5": "tensor(0.0119)",
        "precision@10": "tensor(0.0038)",
        "recall@10": "tensor(0.0354)",
        "hit_rate@10": "tensor(0.0374)",
        "ndcg@10": "tensor(0.0185)",
        "map@10": "tensor(0.0131)",
        "mrr@10": "tensor(0.0138)",
        "precision@20": "tensor(0.0031)",
        "recall@20": "tensor(0.0593)",
        "hit_rate@20": "tensor(0.0626)",
        "ndcg@20": "tensor(0.0246)",
        "map@20": "tensor(0.0147)",
        "mrr@20": "tensor(0.0155)"
      },
      {
        "precision@5": "tensor(0.0048)",
        "recall@5": "tensor(0.0227)",
        "hit_rate@5": "tensor(0.0240)",
        "ndcg@5": "tensor(0.0151)",
        "map@5": "tensor(0.0123)",
        "mrr@5": "tensor(0.0130)",
        "precision@10": "tensor(0.0039)",
        "recall@10": "tensor(0.0369)",
        "hit_rate@10": "tensor(0.0391)",
        "ndcg@10": "tensor(0.0197)",
        "map@10": "tensor(0.0142)",
        "mrr@10": "tensor(0.0149)",
        "precision@20": "tensor(0.0032)",
        "recall@20": "tensor(0.0609)",
        "hit_rate@20": "tensor(0.0641)",
        "ndcg@20": "tensor(0.0257)",
        "map@20": "tensor(0.0158)",
        "mrr@20": "tensor(0.0166)"
      },
      {
        "precision@5": "tensor(0.0049)",
        "recall@5": "tensor(0.0229)",
        "hit_rate@5": "tensor(0.0243)",
        "ndcg@5": "tensor(0.0151)",
        "map@5": "tensor(0.0123)",
        "mrr@5": "tensor(0.0130)",
        "precision@10": "tensor(0.0039)",
        "recall@10": "tensor(0.0370)",
        "hit_rate@10": "tensor(0.0392)",
        "ndcg@10": "tensor(0.0196)",
        "map@10": "tensor(0.0141)",
        "mrr@10": "tensor(0.0149)",
        "precision@20": "tensor(0.0032)",
        "recall@20": "tensor(0.0607)",
        "hit_rate@20": "tensor(0.0640)",
        "ndcg@20": "tensor(0.0256)",
        "map@20": "tensor(0.0157)",
        "mrr@20": "tensor(0.0166)"
      },
      {
        "precision@5": "tensor(0.0048)",
        "recall@5": "tensor(0.0224)",
        "hit_rate@5": "tensor(0.0239)",
        "ndcg@5": "tensor(0.0148)",
        "map@5": "tensor(0.0120)",
        "mrr@5": "tensor(0.0127)",
        "precision@10": "tensor(0.0038)",
        "recall@10": "tensor(0.0360)",
        "hit_rate@10": "tensor(0.0383)",
        "ndcg@10": "tensor(0.0192)",
        "map@10": "tensor(0.0138)",
        "mrr@10": "tensor(0.0146)",
        "precision@20": "tensor(0.0032)",
        "recall@20": "tensor(0.0602)",
        "hit_rate@20": "tensor(0.0635)",
        "ndcg@20": "tensor(0.0253)",
        "map@20": "tensor(0.0154)",
        "mrr@20": "tensor(0.0163)"
      },
      {
        "precision@5": "tensor(0.0048)",
        "recall@5": "tensor(0.0224)",
        "hit_rate@5": "tensor(0.0238)",
        "ndcg@5": "tensor(0.0147)",
        "map@5": "tensor(0.0120)",
        "mrr@5": "tensor(0.0127)",
        "precision@10": "tensor(0.0039)",
        "recall@10": "tensor(0.0364)",
        "hit_rate@10": "tensor(0.0386)",
        "ndcg@10": "tensor(0.0193)",
        "map@10": "tensor(0.0138)",
        "mrr@10": "tensor(0.0146)",
        "precision@20": "tensor(0.0032)",
        "recall@20": "tensor(0.0611)",
        "hit_rate@20": "tensor(0.0643)",
        "ndcg@20": "tensor(0.0255)",
        "map@20": "tensor(0.0155)",
        "mrr@20": "tensor(0.0164)"
      },
      {
        "precision@5": "tensor(0.0048)",
        "recall@5": "tensor(0.0223)",
        "hit_rate@5": "tensor(0.0239)",
        "ndcg@5": "tensor(0.0147)",
        "map@5": "tensor(0.0120)",
        "mrr@5": "tensor(0.0128)",
        "precision@10": "tensor(0.0039)",
        "recall@10": "tensor(0.0370)",
        "hit_rate@10": "tensor(0.0390)",
        "ndcg@10": "tensor(0.0194)",
        "map@10": "tensor(0.0139)",
        "mrr@10": "tensor(0.0147)",
        "precision@20": "tensor(0.0032)",
        "recall@20": "tensor(0.0608)",
        "hit_rate@20": "tensor(0.0642)",
        "ndcg@20": "tensor(0.0255)",
        "map@20": "tensor(0.0155)",
        "mrr@20": "tensor(0.0164)"
      },
      {
        "precision@5": "tensor(0.0045)",
        "recall@5": "tensor(0.0212)",
        "hit_rate@5": "tensor(0.0226)",
        "ndcg@5": "tensor(0.0143)",
        "map@5": "tensor(0.0117)",
        "mrr@5": "tensor(0.0124)",
        "precision@10": "tensor(0.0038)",
        "recall@10": "tensor(0.0361)",
        "hit_rate@10": "tensor(0.0382)",
        "ndcg@10": "tensor(0.0191)",
        "map@10": "tensor(0.0137)",
        "mrr@10": "tensor(0.0145)",
        "precision@20": "tensor(0.0031)",
        "recall@20": "tensor(0.0590)",
        "hit_rate@20": "tensor(0.0623)",
        "ndcg@20": "tensor(0.0249)",
        "map@20": "tensor(0.0153)",
        "mrr@20": "tensor(0.0161)"
      },
      {
        "precision@5": "tensor(0.0046)",
        "recall@5": "tensor(0.0215)",
        "hit_rate@5": "tensor(0.0229)",
        "ndcg@5": "tensor(0.0141)",
        "map@5": "tensor(0.0114)",
        "mrr@5": "tensor(0.0121)",
        "precision@10": "tensor(0.0037)",
        "recall@10": "tensor(0.0347)",
        "hit_rate@10": "tensor(0.0368)",
        "ndcg@10": "tensor(0.0184)",
        "map@10": "tensor(0.0132)",
        "mrr@10": "tensor(0.0140)",
        "precision@20": "tensor(0.0032)",
        "recall@20": "tensor(0.0608)",
        "hit_rate@20": "tensor(0.0639)",
        "ndcg@20": "tensor(0.0250)",
        "map@20": "tensor(0.0150)",
        "mrr@20": "tensor(0.0158)"
      },
      {
        "precision@5": "tensor(0.0045)",
        "recall@5": "tensor(0.0210)",
        "hit_rate@5": "tensor(0.0222)",
        "ndcg@5": "tensor(0.0139)",
        "map@5": "tensor(0.0114)",
        "mrr@5": "tensor(0.0120)",
        "precision@10": "tensor(0.0037)",
        "recall@10": "tensor(0.0351)",
        "hit_rate@10": "tensor(0.0373)",
        "ndcg@10": "tensor(0.0185)",
        "map@10": "tensor(0.0132)",
        "mrr@10": "tensor(0.0140)",
        "precision@20": "tensor(0.0030)",
        "recall@20": "tensor(0.0573)",
        "hit_rate@20": "tensor(0.0607)",
        "ndcg@20": "tensor(0.0241)",
        "map@20": "tensor(0.0147)",
        "mrr@20": "tensor(0.0156)"
      },
      {
        "precision@5": "tensor(0.0046)",
        "recall@5": "tensor(0.0213)",
        "hit_rate@5": "tensor(0.0228)",
        "ndcg@5": "tensor(0.0141)",
        "map@5": "tensor(0.0116)",
        "mrr@5": "tensor(0.0123)",
        "precision@10": "tensor(0.0038)",
        "recall@10": "tensor(0.0360)",
        "hit_rate@10": "tensor(0.0383)",
        "ndcg@10": "tensor(0.0189)",
        "map@10": "tensor(0.0134)",
        "mrr@10": "tensor(0.0143)",
        "precision@20": "tensor(0.0032)",
        "recall@20": "tensor(0.0597)",
        "hit_rate@20": "tensor(0.0630)",
        "ndcg@20": "tensor(0.0249)",
        "map@20": "tensor(0.0150)",
        "mrr@20": "tensor(0.0159)"
      },
      {
        "precision@5": "tensor(0.0046)",
        "recall@5": "tensor(0.0217)",
        "hit_rate@5": "tensor(0.0232)",
        "ndcg@5": "tensor(0.0141)",
        "map@5": "tensor(0.0114)",
        "mrr@5": "tensor(0.0121)",
        "precision@10": "tensor(0.0037)",
        "recall@10": "tensor(0.0347)",
        "hit_rate@10": "tensor(0.0370)",
        "ndcg@10": "tensor(0.0183)",
        "map@10": "tensor(0.0131)",
        "mrr@10": "tensor(0.0139)",
        "precision@20": "tensor(0.0031)",
        "recall@20": "tensor(0.0585)",
        "hit_rate@20": "tensor(0.0619)",
        "ndcg@20": "tensor(0.0244)",
        "map@20": "tensor(0.0147)",
        "mrr@20": "tensor(0.0156)"
      }
    ],
    "training_time": 808.3950364589691
  },
  "test_metrics": {
    "precision@5": "tensor(0.0047)",
    "recall@5": "tensor(0.0211)",
    "hit_rate@5": "tensor(0.0237)",
    "ndcg@5": "tensor(0.0141)",
    "map@5": "tensor(0.0113)",
    "mrr@5": "tensor(0.0126)",
    "precision@10": "tensor(0.0040)",
    "recall@10": "tensor(0.0357)",
    "hit_rate@10": "tensor(0.0402)",
    "ndcg@10": "tensor(0.0189)",
    "map@10": "tensor(0.0132)",
    "mrr@10": "tensor(0.0148)",
    "precision@20": "tensor(0.0034)",
    "recall@20": "tensor(0.0604)",
    "hit_rate@20": "tensor(0.0670)",
    "ndcg@20": "tensor(0.0253)",
    "map@20": "tensor(0.0149)",
    "mrr@20": "tensor(0.0167)"
  },
  "model_info": {
    "model_name": "MMFCN",
    "total_parameters": 1418240,
    "trainable_parameters": 1418240,
    "num_users": 19445,
    "num_items": 7050,
    "num_nodes": 26495,
    "embedding_dim": 64,
    "num_modalities": 2,
    "user_features": [],
    "item_features": [
      "image_feat",
      "text_feat"
    ]
  },
  "config": {
    "data": {
      "data_path": "../autodl-tmp/data/ori_data/baby",
      "user_col": "userID",
      "item_col": "itemID",
      "rating_col": "rating",
      "timestamp_col": null,
      "splitting_label": "x_label",
      "filter_out_new_users": true,
      "negative_sampling": true,
      "sep": "\t",
      "neg_ratio": 1,
      "train_ratio": 0.8,
      "val_ratio": 0.1,
      "test_ratio": 0.1,
      "batch_size": 2048,
      "num_workers": 4,
      "use_time_split": true,
      "graph_from_train_only": true,
      "num_users": 19445,
      "num_items": 7050
    },
    "model": {
      "model_name": "MMGCN_rec",
      "modal_num": 2,
      "emb_dim": 64,
      "layer_num": 2,
      "dropout": 0.3,
      "activation": "prelu",
      "use_batch_norm": true,
      "hidden_dim": 2048,
      "concat": false,
      "k": 3
    },
    "training": {
      "epochs": 1000,
      "learning_rate": 0.0001,
      "weight_decay": 0,
      "optimizer": "adam",
      "scheduler": "plateau",
      "scheduler_patience": 10,
      "scheduler_factor": 0.5,
      "early_stopping_patience": 20,
      "gradient_clip_norm": 1.0,
      "warmup_epochs": 5,
      "eval_every": 1,
      "save_every": 10
    },
    "evaluation": {
      "metrics": [
        "precision",
        "recall",
        "hit_rate",
        "ndcg",
        "map",
        "mrr"
      ],
      "k_values": [
        5,
        10,
        20
      ],
      "test_batch_size": 512,
      "num_negatives": 1,
      "main_metric": "recall"
    },
    "system": {
      "device": "cuda",
      "seed": 42,
      "log_level": "INFO",
      "save_dir": "./checkpoints",
      "log_dir": "./logs",
      "results_dir": "./results",
      "num_gpus": 1,
      "mixed_precision": false
    },
    "graph": {
      "graph_type": "bipartite",
      "add_self_loops": true,
      "normalize_adj": true,
      "edge_weight_type": "cosine",
      "max_neighbors": 50
    }
  }
}